{
 "actions": [],
 "allow_rename": 1,
 "creation": "2025-01-01 00:00:00.000000",
 "doctype": "DocType",
 "editable_grid": 1,
 "engine": "InnoDB",
 "field_order": [
  "follow_up_day",
  "template_type",
  "subject_line",
  "email_body"
 ],
 "fields": [
  {
   "fieldname": "follow_up_day",
   "fieldtype": "Int",
   "in_list_view": 1,
   "label": "Follow-up Day",
   "reqd": 1
  },
  {
   "default": "Follow-up",
   "fieldname": "template_type",
   "fieldtype": "Select",
   "in_list_view": 1,
   "label": "Template Type",
   "options": "Follow-up\nDemo Request\nProposal\nThank You\nBreakup",
   "reqd": 1
  },
  {
   "fieldname": "subject_line",
   "fieldtype": "Data",
   "in_list_view": 1,
   "label": "Subject Line",
   "reqd": 1
  },
  {
   "fieldname": "email_body",
   "fieldtype": "Text Editor",
   "label": "Email Body",
   "reqd": 1
  }
 ],
 "index_web_pages_for_search": 1,
 "istable": 1,
 "links": [],
 "modified": "2025-01-01 00:00:00.000000",
 "modified_by": "Administrator",
 "module": "Lead Intelligence",
 "name": "Follow Up Template",
 "owner": "Administrator",
 "permissions": [],
 "sort_field": "modified",
 "sort_order": "DESC",
 "states": [],
 "track_changes": 1
}